hwpyp/__init__.py
hwpyp/mypy.py
helloworld_prime-0.0.8.dist-info/LICENSE
helloworld_prime-0.0.8.dist-info/METADATA
helloworld_prime-0.0.8.dist-info/WHEEL
helloworld_prime-0.0.8.dist-info/entry_points.txt
helloworld_prime-0.0.8.dist-info/top_level.txt
helloworld_prime-0.0.8.dist-info/RECORD
