Metadata-Version: 2.1
Name: helloworld-prime
Version: 0.0.8
Summary: My first Python Package
Home-page: https://github.com/mahesh-maximus/helloworld-pyp
Author: Luiz Mendes
Author-email: luiz.mendes@primecontrol.com
Project-URL: Bug Tracker, https://github.com/mahesh-maximus/helloworld-pyp/issues
Classifier: Programming Language :: Python :: 3
Classifier: License :: OSI Approved :: MIT License
Requires-Python: >=3.6
License-File: LICENSE
